odoo/addons/pos_product_template/README.rst
odoo/addons/pos_product_template/__init__.py
odoo/addons/pos_product_template/__manifest__.py
odoo/addons/pos_product_template/demo/product_attribute_value.xml
odoo/addons/pos_product_template/demo/product_product.xml
odoo/addons/pos_product_template/i18n/es.po
odoo/addons/pos_product_template/i18n/fr.po
odoo/addons/pos_product_template/i18n/it.po
odoo/addons/pos_product_template/i18n/pos_product_template.pot
odoo/addons/pos_product_template/models/__init__.py
odoo/addons/pos_product_template/models/pos_config.py
odoo/addons/pos_product_template/models/pos_session.py
odoo/addons/pos_product_template/models/product_product.py
odoo/addons/pos_product_template/models/res_config_settings.py
odoo/addons/pos_product_template/readme/CONTRIBUTORS.md
odoo/addons/pos_product_template/readme/DESCRIPTION.md
odoo/addons/pos_product_template/readme/ROADMAP.md
odoo/addons/pos_product_template/readme/USAGE.md
odoo/addons/pos_product_template/static/description/icon.png
odoo/addons/pos_product_template/static/description/index.html
odoo/addons/pos_product_template/static/src/css/ppt.css
odoo/addons/pos_product_template/static/src/img/screenshots/pos_product_template.png
odoo/addons/pos_product_template/static/src/pos/components/product_item/product_item.esm.js
odoo/addons/pos_product_template/static/src/pos/components/product_screen/product_screen.esm.js
odoo/addons/pos_product_template/static/src/pos/components/product_selector/product_selector.esm.js
odoo/addons/pos_product_template/static/src/pos/components/product_selector/product_selector.xml
odoo/addons/pos_product_template/static/src/pos/components/product_template_card/product_template_card.esm.js
odoo/addons/pos_product_template/static/src/pos/components/product_template_card/product_template_card.xml
odoo/addons/pos_product_template/static/src/pos/components/product_widget/product_widget.esm.js
odoo_addon_pos_product_template-17.0.1.0.0.5.dist-info/METADATA
odoo_addon_pos_product_template-17.0.1.0.0.5.dist-info/WHEEL
odoo_addon_pos_product_template-17.0.1.0.0.5.dist-info/top_level.txt
odoo_addon_pos_product_template-17.0.1.0.0.5.dist-info/RECORD
